{
  "collapse-filter": true,
  "search": "-file:index -path:Review",
  "showTags": false,
  "showAttachments": false,
  "hideUnresolved": false,
  "showOrphans": true,
  "collapse-color-groups": true,
  "colorGroups": [
    {
      "query": "path:\"OSI layers\"  ",
      "color": {
        "a": 1,
        "rgb": 14168083
      }
    },
    {
      "query": "tag:#protocol  ",
      "color": {
        "a": 1,
        "rgb": 1779397
      }
    },
    {
      "query": "path:Routing  ",
      "color": {
        "a": 1,
        "rgb": 2212924
      }
    }
  ],
  "collapse-display": false,
  "showArrow": true,
  "textFadeMultiplier": 0,
  "nodeSizeMultiplier": 0.94043659043659,
  "lineSizeMultiplier": 0.818191268191268,
  "collapse-forces": false,
  "centerStrength": 0.425155925155925,
  "repelStrength": 6.09147609147609,
  "linkStrength": 0.437629937629938,
  "linkDistance": 197,
  "scale": 0.8814265637106395,
  "close": false
}